sphinx_idl/__init__.py
sphinx_idl/auto.py
sphinx_idl/domain.py
sphinx_idl/parser.py
sphinx_idl-0.1.dist-info/LICENSE
sphinx_idl-0.1.dist-info/METADATA
sphinx_idl-0.1.dist-info/WHEEL
sphinx_idl-0.1.dist-info/top_level.txt
sphinx_idl-0.1.dist-info/RECORD
